surebet/__init__.py
surebet/arb.py
surebet/cli.py
surebet/converter.py
surebet/surebet.py
surebet-0.1.2.dist-info/METADATA
surebet-0.1.2.dist-info/RECORD
surebet-0.1.2.dist-info/WHEEL
surebet-0.1.2.dist-info/entry_points.txt
surebet-0.1.2.dist-info/top_level.txt
