Metadata-Version: 2.1
Name: surebet
Version: 0.1.2
Summary: surebet is Python sport betting library allowing you to easily convert betting odds, calculate returns, calculate arbitrage betting opportunities and more
Home-page: https://github.com/HintikkaKimmo/surebet
Author: Kimmo Hintikka
Author-email: hintikkakimmo@gmail.com
License: MIT License
Keywords: surebet
Platform: UNKNOWN
Classifier: Development Status :: 2 - Pre-Alpha
Classifier: Intended Audience :: Developers
Classifier: License :: OSI Approved :: MIT License
Classifier: Natural Language :: English
Classifier: Programming Language :: Python :: 3
Classifier: Programming Language :: Python :: 3.4
Classifier: Programming Language :: Python :: 3.5
Classifier: Programming Language :: Python :: 3.6
